{
    "使用四叶草总和": {
        "绑定": {
            "1级四叶草": 2599,
            "3级四叶草": 1818,
            "2级四叶草": 2520,
            "4级四叶草": 1207,
            "5级四叶草": 92,
            "超能四叶草": 2,
            "6级四叶草": 15
        },
        "不绑": {
            "1级四叶草": 3806,
            "3级四叶草": 959,
            "2级四叶草": 1465,
            "4级四叶草": 0,
            "5级四叶草": 0
        }
    },
    "使用香料总和": {
        "绑定": {
            "天然香料": 280,
            "上等香料": 280,
            "秘制香料": 4795,
            "极品香料": 31520,
            "皇室香料": 9870,
            "魔幻香料": 8575,
            "精灵香料": 210
        },
        "不绑": {
            "不放香料": 31900,
            "天然香料": 41555,
            "上等香料": 29390,
            "秘制香料": 4730,
            "极品香料": 900,
            "皇室香料": 50,
            "魔幻香料": 0
        }
    },
    "使用卡片总和": {
        "绑定": {
            "0": 10,
            "1": 82,
            "2": 100,
            "3": 1019,
            "4": 7516,
            "5": 6031,
            "6": 3351,
            "7": 1078,
            "8": 656,
            "9": 206,
            "10": 30
        },
        "不绑": {
            "0": 6444,
            "1": 9244,
            "2": 7989,
            "3": 9763,
            "4": 4055,
            "5": 3650,
            "6": 1050,
            "7": 320,
            "8": 188,
            "9": 0
        }
    },
    "强化出卡片总和": {
        "绑定": {
            "0": 0,
            "1": 22,
            "2": 12,
            "3": 24,
            "4": 160,
            "5": 868,
            "6": 317,
            "7": 281,
            "8": 171,
            "9": 59,
            "10": 12
        },
        "不绑": {
            "0": 0,
            "1": 0,
            "2": 0,
            "3": 0,
            "4": 0,
            "5": 0,
            "6": 0,
            "7": 0,
            "8": 0,
            "9": 0
        }
    },
    "强化次数总和": {
        "0-1": 526,
        "1-2": 938,
        "2-3": 8037,
        "3-4": 4830,
        "4-5": 6323,
        "5-6": 4903,
        "6-7": 2334,
        "7-8": 1222,
        "8-9": 422,
        "9-10": 88,
        "10-11": 15
    },
    "成功次数总和": {
        "0-1": 514,
        "1-2": 933,
        "2-3": 6521,
        "3-4": 2453,
        "4-5": 3827,
        "5-6": 2210,
        "6-7": 1224,
        "7-8": 805,
        "8-9": 260,
        "9-10": 34,
        "10-11": 2
    },
    "使用金币总额": 2983744
}